constattr/__init__.py
constattr/const_enforcer_meta.py
constattr/decorators.py
constattr/exceptions.py
constattr/tests/__init__.py
constattr/tests/test_decorators.py
constattr-0.0.4.dist-info/LICENSE
constattr-0.0.4.dist-info/METADATA
constattr-0.0.4.dist-info/WHEEL
constattr-0.0.4.dist-info/top_level.txt
constattr-0.0.4.dist-info/RECORD
